<routes><route id="0" town="Town12">
      <weathers>
         <weather route_percentage="0.0" cloudiness="100.0" precipitation="4.0" precipitation_deposits="4.0" wetness="6.0" wind_intensity="25.0" sun_azimuth_angle="45.0" sun_altitude_angle="80.0" fog_density="2.0" />
         <weather route_percentage="100.0" cloudiness="20.0" precipitation="4.0" precipitation_deposits="50.0" wetness="80.0" wind_intensity="100.0" sun_azimuth_angle="270.0" sun_altitude_angle="15.0" fog_density="6.0" />
      </weathers>
      <waypoints>
         <position x="2718.1" y="-477.0" z="332.1" />
         <position x="2783.4" y="-564.0" z="331.8" />
      </waypoints>
      <scenarios>
         <scenario name="VehicleTurningRoutePedestrian_1" type="VehicleTurningRoutePedestrian">
            <trigger_point x="2738.3" y="-477.3" z="331.2" yaw="-0.3" />
         </scenario>
      </scenarios>
   </route>
</routes>