<routes><route id="0" town="Town12">
      <weathers>
         <weather route_percentage="0.0" cloudiness="0.0" precipitation="4.0" precipitation_deposits="80.0" wetness="100.0" wind_intensity="50.0" sun_azimuth_angle="135.0" sun_altitude_angle="-30.0" fog_density="70.0" />
         <weather route_percentage="100.0" cloudiness="2.0" precipitation="40.0" precipitation_deposits="0.0" wetness="10.0" wind_intensity="50.0" sun_azimuth_angle="45.0" sun_altitude_angle="60.0" fog_density="3.0" />
      </weathers>
      <waypoints>
         <position x="2375.8" y="-823.9" z="339.0" />
         <position x="2412.9" y="-906.5" z="338.2" />
      </waypoints>
      <scenarios>
         <scenario name="BlockedIntersection_1" type="BlockedIntersection">
            <trigger_point x="2375.8" y="-844.0" z="338.9" yaw="269.8" />
         </scenario>
      </scenarios>
   </route>
</routes>