<?xml version="1.0" ?>
<routes>
   <route id="0" town="Town12">
      <weathers>
         <weather route_percentage="0.0" cloudiness="0.0" precipitation="15.0" precipitation_deposits="30.0" wetness="0.0" wind_intensity="30.0" sun_azimuth_angle="360.0" sun_altitude_angle="10.0" fog_density="7.0"/>
         <weather route_percentage="100.0" cloudiness="80.0" precipitation="100.0" precipitation_deposits="100.0" wetness="6.0" wind_intensity="10.0" sun_azimuth_angle="180.0" sun_altitude_angle="-30.0" fog_density="6.0"/>
      </weathers>
      <waypoints>
         <position x="-283.6" y="5118.0" z="373.7"/>
         <position x="-231.1" y="5241.1" z="373.0"/>
         <position x="-216.9" y="5274.4" z="372.8"/>
      </waypoints>
      <scenarios>
         <scenario name="ConstructionObstacleTwoWays_1" type="ConstructionObstacleTwoWays">
            <trigger_point x="-275.7" y="5136.5" z="373.6" yaw="66.9"/>
            <distance value="80"/>
            <frequency from="45" to="115"/>
         </scenario>
      </scenarios>
   </route>
</routes>
